odoo/addons/purchase_order_ubl/README.rst
odoo/addons/purchase_order_ubl/__init__.py
odoo/addons/purchase_order_ubl/__manifest__.py
odoo/addons/purchase_order_ubl/i18n/es.po
odoo/addons/purchase_order_ubl/i18n/fr.po
odoo/addons/purchase_order_ubl/i18n/purchase_order_ubl.pot
odoo/addons/purchase_order_ubl/models/__init__.py
odoo/addons/purchase_order_ubl/models/purchase.py
odoo/addons/purchase_order_ubl/models/report.py
odoo/addons/purchase_order_ubl/readme/CONTRIBUTORS.rst
odoo/addons/purchase_order_ubl/readme/DESCRIPTION.rst
odoo/addons/purchase_order_ubl/static/description/icon.png
odoo/addons/purchase_order_ubl/static/description/index.html
odoo/addons/purchase_order_ubl/tests/__init__.py
odoo/addons/purchase_order_ubl/tests/test_ubl_generate.py
odoo14_addon_purchase_order_ubl-14.0.1.2.0.dist-info/METADATA
odoo14_addon_purchase_order_ubl-14.0.1.2.0.dist-info/WHEEL
odoo14_addon_purchase_order_ubl-14.0.1.2.0.dist-info/top_level.txt
odoo14_addon_purchase_order_ubl-14.0.1.2.0.dist-info/RECORD
