Metadata-Version: 2.1
Name: odoo14-addon-purchase_order_ubl
Version: 14.0.1.2.0
Summary: Embed UBL XML file inside the PDF purchase order
Home-page: https://github.com/OCA/edi
Author: Akretion,Odoo Community Association (OCA)
Author-email: support@odoo-community.org
License: AGPL-3
Classifier: Programming Language :: Python
Classifier: Framework :: Odoo
Classifier: Framework :: Odoo :: 14.0
Classifier: License :: OSI Approved :: GNU Affero General Public License v3
Requires-Python: >=3.6
Requires-Dist: odoo14-addon-base-ubl
Requires-Dist: odoo <14.1dev,>=14.0a
